gbq_connector/__init__.py
gbq_connector/bigquery_client.py
gbq_connector/cloud_client.py
gbq_connector/dbt_client.py
gbq_connector/exceptions.py
gbq_connector-4.2.dist-info/LICENSE
gbq_connector-4.2.dist-info/METADATA
gbq_connector-4.2.dist-info/WHEEL
gbq_connector-4.2.dist-info/top_level.txt
gbq_connector-4.2.dist-info/RECORD
